webautomate/__init__.py
webautomate/browser_controller.py
webautomate/test.py
webautomate-0.2.0.dist-info/LICENSE
webautomate-0.2.0.dist-info/METADATA
webautomate-0.2.0.dist-info/WHEEL
webautomate-0.2.0.dist-info/top_level.txt
webautomate-0.2.0.dist-info/RECORD
